PRPG.v
module PRPG (Q,clk,rst);
    input clk,rst;
    output [2:0]Q;
    reg [2:0]Q;

    always @(posedge clk) begin
        if (rst) begin
            Q<=3'b110;
        end
        else begin
        Q[0]<=Q[2]^Q[0];
        Q[1]<=Q[0];
        Q[2]<=Q[1];
        end
    end
endmodule

PRPG_tb.v
module  PRPG_tb;
  reg clk,rst;
  wire [2:0]Q;
  parameter PERIOD=20;
  parameter real DUTY_CYCLE=0.5;
  parameter OFFSET=0;
initial begin
  #OFFSET;
  forever begin
    clk=1'b1;
    #(PERIOD-(PERIOD*DUTY_CYCLE)) clk=1'b0;
    #(PERIOD*DUTY_CYCLE);
  end
end
initial begin
  rst=1'b1;
  #20   rst=1'b0;
  #200 $finish;
end
initial begin
$dumpfile("PRPG.vcd");
  $dumpvars(0, PRPG_tb);
end
  PRPG PRPG_tb(
    .clk(clk),
    .rst(rst),
    .Q(Q)
  );
endmodule

PRPG.vcd
$date
	Thu May 19 11:48:26 2022
$end
$version
	Icarus Verilog
$end
$timescale
	1s
$end
$scope module PRPG_tb $end
$scope module PRPG_tb $end
$var wire 1 ! clk $end
$var wire 1 " rst $end
$var reg 3 # Q [2:0] $end
$upscope $end
$upscope $end
$enddefinitions $end
#0
$dumpvars
b110 #
1"
1!
$end
#10
0!
#20
b101 #
1!
0"
#30
0!
#40
b10 #
1!
#50
0!
#60
b100 #
1!
#70
0!
#80
b1 #
1!
#90
0!
#100
b11 #
1!
#110
0!
#120
b111 #
1!
#130
0!
#140
b110 #
1!
#150
0!
#160
b101 #
1!
#170
0!
#180
b10 #
1!
#190
0!
#200
b100 #
1!
#210
0!
#220
b1 #
1!
